aoba_discord_bot/__init__.py
aoba_discord_bot/aoba_checks.py
aoba_discord_bot/bot.py
aoba_discord_bot/cli.py
aoba_discord_bot/db_models.py
aoba_discord_bot/formatting.py
aoba_discord_bot/cogs/__init__.py
aoba_discord_bot/cogs/admin/__init__.py
aoba_discord_bot/cogs/admin/admin_cog.py
aoba_discord_bot/cogs/bot_admin/__init__.py
aoba_discord_bot/cogs/bot_admin/bot_admin_cog.py
aoba_discord_bot/cogs/osu/__init__.py
aoba_discord_bot/cogs/osu/osu_api_cog.py
aoba_discord_bot/cogs/user/__init__.py
aoba_discord_bot/cogs/user/user_cog.py
aoba_discord_bot-0.1.13.dist-info/LICENSE
aoba_discord_bot-0.1.13.dist-info/METADATA
aoba_discord_bot-0.1.13.dist-info/WHEEL
aoba_discord_bot-0.1.13.dist-info/entry_points.txt
aoba_discord_bot-0.1.13.dist-info/top_level.txt
aoba_discord_bot-0.1.13.dist-info/RECORD
