Metadata-Version: 2.1
Name: aoba-discord-bot
Version: 0.1.13
Summary: Aoba, the cutest Python Discord bot in all of GitHub.
Home-page: https://github.com/douglascdev/aoba_discord_bot
Author: Douglas Carvalho
Author-email: douglasc.dev@gmail.com
License: MIT license
Keywords: aoba_discord_bot
Platform: UNKNOWN
Classifier: Development Status :: 2 - Pre-Alpha
Classifier: Intended Audience :: Developers
Classifier: License :: OSI Approved :: MIT License
Classifier: Natural Language :: English
Classifier: Programming Language :: Python :: 3
Classifier: Programming Language :: Python :: 3.6
Classifier: Programming Language :: Python :: 3.7
Classifier: Programming Language :: Python :: 3.8
Classifier: Programming Language :: Python :: 3.9
Requires-Python: >=3.6
License-File: LICENSE
Requires-Dist: Click (>=7.0)
Requires-Dist: discord.py (>=1.7.3)
Requires-Dist: sqlalchemy (>=1.4.22)
Requires-Dist: requests (>=2.26.0)
Requires-Dist: beautifulsoup4 (>=4.9.3)
